django_sendpdf-2.0.1.dist-info/METADATA
django_sendpdf-2.0.1.dist-info/RECORD
django_sendpdf-2.0.1.dist-info/WHEEL
django_sendpdf-2.0.1.dist-info/top_level.txt
sendpdf/__init__.py
sendpdf/apps.py
sendpdf/topdf.py
sendpdf/urls.py
sendpdf/views.py
sendpdf/static/sendpdf/css/print.css
sendpdf/static/sendpdf/img/logo.png
sendpdf/templates/sendpdf/docs/account_statement.html
sendpdf/templates/sendpdf/email/statement.html
sendpdf/templates/sendpdf/email/statement.txt
sendpdf/templatetags/__init__.py
sendpdf/templatetags/pdftags.py
tests/__init__.py
tests/test_settings.py
tests/tests.py
