Metadata-Version: 2.1
Name: django-sendpdf
Version: 2.0.1
Summary: Generate PDF from html templates and print, view or send via email
Home-page: http://django-sendpdf.readthedocs.io/en/latest
Author: James Wanderi
Author-email: wanderikinyanjui@gmail.com
License: MIT License
Download-URL: https://github.com/wanderijames/django-sendpdf
Keywords: django,PDF
Platform: UNKNOWN
Classifier: Environment :: Web Environment
Classifier: Framework :: Django
Classifier: Intended Audience :: Developers
Classifier: Natural Language :: English
Classifier: License :: OSI Approved :: MIT License
Classifier: Operating System :: OS Independent
Classifier: Development Status :: 4 - Beta
Classifier: Programming Language :: Python
Classifier: Programming Language :: Python :: 3
Classifier: Programming Language :: Python :: 3.6
Classifier: Programming Language :: Python :: 3.7
Classifier: Programming Language :: Python :: 3.8
Classifier: Topic :: Internet :: WWW/HTTP
Classifier: Topic :: Internet :: WWW/HTTP :: Dynamic Content
Requires-Dist: pdfkit
